odoo10_addon_partner_daytopay-10.0.1.0.1.99.dev7-py2.7-nspkg.pth
odoo/addons/partner_daytopay/README.rst
odoo/addons/partner_daytopay/__init__.py
odoo/addons/partner_daytopay/__manifest__.py
odoo/addons/partner_daytopay/i18n/es.po
odoo/addons/partner_daytopay/i18n/fr.po
odoo/addons/partner_daytopay/i18n/nl_NL.po
odoo/addons/partner_daytopay/i18n/partner_daytopay.pot
odoo/addons/partner_daytopay/models/__init__.py
odoo/addons/partner_daytopay/models/res_partner.py
odoo/addons/partner_daytopay/static/description/icon.png
odoo/addons/partner_daytopay/views/res_partner.xml
odoo10_addon_partner_daytopay-10.0.1.0.1.99.dev7.dist-info/METADATA
odoo10_addon_partner_daytopay-10.0.1.0.1.99.dev7.dist-info/RECORD
odoo10_addon_partner_daytopay-10.0.1.0.1.99.dev7.dist-info/WHEEL
odoo10_addon_partner_daytopay-10.0.1.0.1.99.dev7.dist-info/namespace_packages.txt
odoo10_addon_partner_daytopay-10.0.1.0.1.99.dev7.dist-info/top_level.txt
