Metadata-Version: 2.1
Name: odoo10-addon-partner-daytopay
Version: 10.0.1.0.1.99.dev7
Summary: Adds receivables and payables statistics to partners
Home-page: http://www.ursainfosystems.com
Author: Ursa Information Systems, Odoo Community Association (OCA)
Author-email: support@odoo-community.org
License: AGPL-3
Platform: UNKNOWN
Classifier: Programming Language :: Python
Classifier: Framework :: Odoo
Classifier: License :: OSI Approved :: GNU Affero General Public License v3
Requires-Python: ~=2.7
Requires-Dist: odoo (<10.1dev,>=10.0)
